gummi/__init__.py
gummi/check.py
gummi/constants.py
gummi/detach.py
gummi/exit_codes.py
gummi/init.py
gummi/main.py
gummi/run.py
gummi/update.py
gummi-1.3.4.dist-info/LICENSE
gummi-1.3.4.dist-info/METADATA
gummi-1.3.4.dist-info/WHEEL
gummi-1.3.4.dist-info/entry_points.txt
gummi-1.3.4.dist-info/top_level.txt
gummi-1.3.4.dist-info/RECORD
