Metadata-Version: 2.1
Name: gummi
Version: 1.3.4
Summary: Manage your LaTeX templates with ease.
Home-page: https://github.com/seboschtion/gummi
Author: sebastian
Author-email: sebastian.hug@outlook.com
License: UNKNOWN
Platform: UNKNOWN
Classifier: Programming Language :: Python :: 3
Classifier: License :: OSI Approved :: MIT License
Classifier: Operating System :: OS Independent
Requires-Dist: bleach (==3.1.0)
Requires-Dist: certifi (==2019.11.28)
Requires-Dist: chardet (==3.0.4)
Requires-Dist: docutils (==0.15.2)
Requires-Dist: gitdb2 (==2.0.5)
Requires-Dist: GitPython (==2.1.11)
Requires-Dist: idna (==2.8)
Requires-Dist: pkginfo (==1.5.0.1)
Requires-Dist: Pygments (==2.5.2)
Requires-Dist: readme-renderer (==24.0)
Requires-Dist: requests (==2.22.0)
Requires-Dist: requests-toolbelt (==0.9.1)
Requires-Dist: rfc3987 (==1.3.8)
Requires-Dist: six (==1.13.0)
Requires-Dist: smmap2 (==2.0.5)
Requires-Dist: tqdm (==4.40.1)
Requires-Dist: twine (==1.13.0)
Requires-Dist: urllib3 (==1.25.7)
Requires-Dist: webencodings (==0.5.1)
